{
  "id": "MA3032",
  "IntroText": {
    "Type": "PlainText",
    "Content": "請將單位進行換算"
  },
  "GameType": "Track",
  "GameConfig": {},
  "Hint": {},
  "Questions": [
    {
      "Question": [
        {
          "name": "TextOnly",
          "Data": {
            "Text": "3分鐘",
            "Size": "title-large"
          },
          "Selections": ["A.180秒", "C.90秒", "B.160秒"],
          "AnswerIndex": 0
        },
        {
          "name": "TextOnly",
          "Data": {
            "Text": "9分鐘",
            "Size": "title-large"
          },
          "Selections": ["A.540秒", "B.450秒", "C.54秒"],
          "AnswerIndex": 0
        },
        {
          "name": "TextOnly",
          "Data": {
            "Text": "5分鐘",
            "Size": "title-large"
          },
          "Selections": ["C.30秒", "B.270秒", "A.300秒"],
          "AnswerIndex": 2
        },
        {
          "name": "TextOnly",
          "Data": {
            "Text": "8分鐘",
            "Size": "title-large"
          },
          "Selections": ["A.480秒", "B.450秒", "C.48秒"],
          "AnswerIndex": 0
        },
        {
          "name": "TextOnly",
          "Data": {
            "Text": "7分鐘",
            "Size": "title-large"
          },
          "Selections": ["B.120秒", "A.420秒", "C.84秒"],
          "AnswerIndex": 1
        }
      ]
    },
    {
      "Question": [
        {
          "name": "TextOnly",
          "Data": {
            "Text": "62毫米",
            "Size": "title-large"
          },
          "Selections": ["C.6公分2毫米", "B.62公分", "A.2公分6毫米"],
          "AnswerIndex": 0
        },
        {
          "name": "TextOnly",
          "Data": {
            "Text": "20毫米",
            "Size": "title-large"
          },
          "Selections": ["C.2公分", "A.2公分10毫米", "B.20公分"],
          "AnswerIndex": 0
        },
        {
          "name": "TextOnly",
          "Data": {
            "Text": "48毫米",
            "Size": "title-large"
          },
          "Selections": ["C.4公分8毫米", "A.8公分4毫米", "B.48公分"],
          "AnswerIndex": 0
        },
        {
          "name": "TextOnly",
          "Data": {
            "Text": "37毫米",
            "Size": "title-large"
          },
          "Selections": ["C.3公分7毫米", "B.37公分", "A.7公分3毫米"],
          "AnswerIndex": 0
        },
        {
          "name": "TextOnly",
          "Data": {
            "Text": "50毫米",
            "Size": "title-large"
          },
          "Selections": ["C.5公分", "B.50公分", "A.1公分50毫米"],
          "AnswerIndex": 0
        }
      ]
    },
    {
      "Question": [
        {
          "name": "TextOnly",
          "Data": {
            "Text": "6公分2毫米",
            "Size": "title-large"
          },
          "Selections": ["B.62毫米", "A.620毫米", "C.62公分"],
          "AnswerIndex": 0
        },
        {
          "name": "TextOnly",
          "Data": {
            "Text": "2公分4毫米",
            "Size": "title-large"
          },
          "Selections": ["B.24毫米", "A.240毫米", "C.24公分"],
          "AnswerIndex": 0
        },
        {
          "name": "TextOnly",
          "Data": {
            "Text": "5公分1毫米",
            "Size": "title-large"
          },
          "Selections": ["B.51毫米", "C.51公分", "A.510毫米"],
          "AnswerIndex": 0
        },
        {
          "name": "TextOnly",
          "Data": {
            "Text": "4公分9毫米",
            "Size": "title-large"
          },
          "Selections": ["B.49毫米", "C.49公分", "A.490毫米"],
          "AnswerIndex": 0
        },
        {
          "name": "TextOnly",
          "Data": {
            "Text": "3公分8毫米",
            "Size": "title-large"
          },
          "Selections": ["B.38毫米", "C.38公分", "A.380毫米"],
          "AnswerIndex": 0
        }
      ]
    },
    {
      "Question": [
        {
          "name": "TextOnly",
          "Data": {
            "Text": "10公分2毫米",
            "Size": "title-large"
          },
          "Selections": ["A.102毫米", "C.102公分", "B.120毫米"],
          "AnswerIndex": 0
        },
        {
          "name": "TextOnly",
          "Data": {
            "Text": "20公分5毫米",
            "Size": "title-large"
          },
          "Selections": ["A.205毫米", "C.205公分", "B.25毫米"],
          "AnswerIndex": 0
        },
        {
          "name": "TextOnly",
          "Data": {
            "Text": "10公分9毫米",
            "Size": "title-large"
          },
          "Selections": ["B.190毫米", "A.109毫米", "C.109公分"],
          "AnswerIndex": 1
        },
        {
          "name": "TextOnly",
          "Data": {
            "Text": "10公分1毫米",
            "Size": "title-large"
          },
          "Selections": ["A.101毫米", "C.101公分", "B.110毫米"],
          "AnswerIndex": 0
        },
        {
          "name": "TextOnly",
          "Data": {
            "Text": "20公分2毫米",
            "Size": "title-large"
          },
          "Selections": ["C.202公分", "B.220毫米", "A.202毫米"],
          "AnswerIndex": 2
        }
      ]
    },
    {
      "Question": [
        {
          "name": "TextOnly",
          "Data": {
            "Text": "104毫米",
            "Size": "title-large"
          },
          "Selections": ["B.10公分4毫米", "C.10公分40毫米", "A.1公分4毫米"],
          "AnswerIndex": 0
        },
        {
          "name": "TextOnly",
          "Data": {
            "Text": "203毫米",
            "Size": "title-large"
          },
          "Selections": ["B.20公分3毫米", "C.30公分2毫米", "A.2公分3毫米"],
          "AnswerIndex": 0
        },
        {
          "name": "TextOnly",
          "Data": {
            "Text": "189毫米",
            "Size": "title-large"
          },
          "Selections": ["B.18公分9毫米", "C.1公分98毫米", "A.1公分89毫米"],
          "AnswerIndex": 0
        },
        {
          "name": "TextOnly",
          "Data": {
            "Text": "107毫米",
            "Size": "title-large"
          },
          "Selections": ["A.1公分7毫米", "C.10公分70毫米", "B.10公分7毫米"],
          "AnswerIndex": 2
        },
        {
          "name": "TextOnly",
          "Data": {
            "Text": "155毫米",
            "Size": "title-large"
          },
          "Selections": ["B.15公分5毫米", "A.1公分55毫米", "C.1公分15毫米"],
          "AnswerIndex": 0
        }
      ]
    }
  ]
}
